{
  "feature_id": "BD-SMP-002",
  "feature_name": "入力信号チャタリング抑止・診断カウンタ機能",
  "overall": "条件付き合格",
  "summary": {
    "PASS": 7,
    "WARN": 6,
    "FAIL": 0
  },
  "items": [
    {
      "check_id": "BRC-A01",
      "category": "要件整合",
      "status": "PASS",
      "comment": "記載あり。基本設計レベルとして妥当。"
    },
    {
      "check_id": "BRC-A02",
      "category": "RT/TS分離",
      "status": "PASS",
      "comment": "記載あり。基本設計レベルとして妥当。"
    },
    {
      "check_id": "BRC-A03",
      "category": "共有データ",
      "status": "WARN",
      "comment": "共有グローバル変数の読取元/書込元はあるが、更新順序・排他不要条件は詳細設計で確定が必要。"
    },
    {
      "check_id": "BRC-A04",
      "category": "API",
      "status": "PASS",
      "comment": "記載あり。基本設計レベルとして妥当。"
    },
    {
      "check_id": "BRC-A05",
      "category": "状態遷移",
      "status": "PASS",
      "comment": "記載あり。基本設計レベルとして妥当。"
    },
    {
      "check_id": "BRC-A06",
      "category": "安全",
      "status": "PASS",
      "comment": "記載あり。基本設計レベルとして妥当。"
    },
    {
      "check_id": "BRC-A07",
      "category": "性能",
      "status": "WARN",
      "comment": "RT周期内の目標はあるが、最大件数時のワーストケース根拠は詳細設計で補足が必要。"
    },
    {
      "check_id": "BRC-A08",
      "category": "影響調査",
      "status": "PASS",
      "comment": "記載あり。基本設計レベルとして妥当。"
    },
    {
      "check_id": "BRC-A09",
      "category": "テスト",
      "status": "WARN",
      "comment": "build/testコマンドは記載あり。追加テストケースIDと期待値は詳細設計またはテスト仕様書で確定が必要。"
    },
    {
      "check_id": "BRC-A10",
      "category": "JSON相互変換",
      "status": "PASS",
      "comment": "記載あり。基本設計レベルとして妥当。"
    },
    {
      "check_id": "BRC-WARN",
      "category": "機能固有リスク",
      "status": "WARN",
      "comment": "フィルタ閾値の初期値と信号種別ごとの妥当性を詳細設計で確定すること"
    },
    {
      "check_id": "BRC-WARN",
      "category": "機能固有リスク",
      "status": "WARN",
      "comment": "API経由でパラメータ変更する場合の反映タイミングを明確化すること"
    },
    {
      "check_id": "BRC-WARN",
      "category": "機能固有リスク",
      "status": "WARN",
      "comment": "診断カウンタのオーバーフロー時動作を詳細設計で定義すること"
    }
  ]
}